connectionhandler/__init__.py
connectionhandler/get_handler.py
connectionhandler/connectiontypes/__init__.py
connectionhandler/connectiontypes/database_handler.py
connectionhandler/connectiontypes/dynamo_handler.py
connectionhandler/connectiontypes/mssql_handler.py
connectionhandler/connectiontypes/mysql_handler.py
connectionhandler/connectiontypes/postgres_handler.py
connectionhandler/connectiontypes/sql_handler.py
connectionhandler/dbImxLog/__init__.py
connectionhandler/dbImxLog/dbImxLog.py
connectionhandler/dbImxLog/sampleLoggingHandler.py
connectionhandler/enums/__init__.py
connectionhandler/enums/db_type.py
ConnectionHandler-0.0.81.dist-info/LICENSE.txt
ConnectionHandler-0.0.81.dist-info/METADATA
ConnectionHandler-0.0.81.dist-info/WHEEL
ConnectionHandler-0.0.81.dist-info/top_level.txt
ConnectionHandler-0.0.81.dist-info/RECORD
