Metadata-Version: 2.1
Name: ConnectionHandler
Version: 0.0.81
Summary: 'AWS Database Connection Handler'
License-File: LICENSE.txt
